.gitignore
.pylintrc
.readthedocs.yml
CODE_OF_CONDUCT.md
LICENSE
README.rst
circuitpython_base64.py
requirements.txt
setup.py
.github/workflows/build.yml
.github/workflows/release.yml
circuitpython_base64.egg-info/PKG-INFO
circuitpython_base64.egg-info/SOURCES.txt
circuitpython_base64.egg-info/dependency_links.txt
circuitpython_base64.egg-info/requires.txt
circuitpython_base64.egg-info/top_level.txt
docs/api.rst
docs/conf.py
docs/examples.rst
docs/index.rst
docs/_static/favicon.ico
examples/base64_simpletest.py