Metadata-Version: 2.1
Name: circuitpython-base64
Version: 0.3.1
Summary: RFC 3548: Base16, Base32, Base64 Data Encodings
Home-page: https://github.com/jimbobbennett/CircuitPython_base64
Author: Jim Bennett
Author-email: jim.bennett@microsoft.com
License: MIT
Keywords: adafruit blinka circuitpython micropython base64 encoding
Platform: UNKNOWN
Classifier: Development Status :: 3 - Alpha
Classifier: Intended Audience :: Developers
Classifier: Topic :: Software Development :: Libraries
Classifier: Topic :: System :: Hardware
Classifier: License :: OSI Approved :: MIT License
Classifier: Programming Language :: Python :: 3
Classifier: Programming Language :: Python :: 3.4
Classifier: Programming Language :: Python :: 3.5
